pyraid/__init__.py
pyraid/_version.py
pyraid/api.py
pyraid/request_handler.py
pyraid/utils.py
pyraid/models/__init__.py
pyraid/models/base.py
pyraid/models/docker.py
pyraid/models/peripherals.py
pyraid/models/server.py
pyraid/models/vm.py
pyraid-0.0.2.dist-info/METADATA
pyraid-0.0.2.dist-info/WHEEL
pyraid-0.0.2.dist-info/top_level.txt
pyraid-0.0.2.dist-info/RECORD
